{
  "response": {
    "success": true,
    "groups": [
      {
        "gid": "184"
      },
      {
        "gid": "2151"
      },
      {
        "gid": "148845"
      },
      {
        "gid": "275018"
      },
      {
        "gid": "508934"
      },
      {
        "gid": "590561"
      },
      {
        "gid": "595481"
      },
      {
        "gid": "1582249"
      },
      {
        "gid": "1585446"
      },
      {
        "gid": "1799923"
      },
      {
        "gid": "2502890"
      },
      {
        "gid": "3134472"
      },
      {
        "gid": "3284297"
      },
      {
        "gid": "3316128"
      },
      {
        "gid": "3558400"
      },
      {
        "gid": "3703047"
      },
      {
        "gid": "4243811"
      },
      {
        "gid": "4397053"
      },
      {
        "gid": "4458811"
      },
      {
        "gid": "4597640"
      },
      {
        "gid": "4741524"
      },
      {
        "gid": "4755837"
      },
      {
        "gid": "4759298"
      },
      {
        "gid": "4857785"
      },
      {
        "gid": "4870468"
      },
      {
        "gid": "5377070"
      },
      {
        "gid": "5474498"
      },
      {
        "gid": "5531565"
      },
      {
        "gid": "6101713"
      },
      {
        "gid": "6144970"
      },
      {
        "gid": "6148844"
      },
      {
        "gid": "6201122"
      },
      {
        "gid": "6645339"
      },
      {
        "gid": "6810992"
      },
      {
        "gid": "7126816"
      },
      {
        "gid": "7238336"
      },
      {
        "gid": "8328525"
      },
      {
        "gid": "9136732"
      },
      {
        "gid": "10141695"
      },
      {
        "gid": "10494854"
      },
      {
        "gid": "10546736"
      },
      {
        "gid": "12064364"
      },
      {
        "gid": "23740371"
      },
      {
        "gid": "25174872"
      },
      {
        "gid": "25333561"
      },
      {
        "gid": "25339032"
      },
      {
        "gid": "25339077"
      },
      {
        "gid": "25588535"
      },
      {
        "gid": "25883387"
      },
      {
        "gid": "26305398"
      },
      {
        "gid": "26482945"
      },
      {
        "gid": "26756900"
      },
      {
        "gid": "27647307"
      },
      {
        "gid": "27738092"
      },
      {
        "gid": "28934479"
      },
      {
        "gid": "29087962"
      },
      {
        "gid": "30560232"
      },
      {
        "gid": "30718459"
      },
      {
        "gid": "30897473"
      },
      {
        "gid": "30945277"
      },
      {
        "gid": "31013613"
      },
      {
        "gid": "31255098"
      },
      {
        "gid": "31404391"
      },
      {
        "gid": "31511885"
      },
      {
        "gid": "31512703"
      },
      {
        "gid": "31711203"
      },
      {
        "gid": "31721797"
      },
      {
        "gid": "31859042"
      },
      {
        "gid": "32791864"
      },
      {
        "gid": "32811639"
      },
      {
        "gid": "32965397"
      },
      {
        "gid": "33038843"
      },
      {
        "gid": "33171098"
      },
      {
        "gid": "33202756"
      },
      {
        "gid": "33228119"
      },
      {
        "gid": "33245052"
      },
      {
        "gid": "33349060"
      },
      {
        "gid": "33459075"
      },
      {
        "gid": "33512364"
      },
      {
        "gid": "33857746"
      },
      {
        "gid": "34012997"
      },
      {
        "gid": "34079319"
      },
      {
        "gid": "34237546"
      },
      {
        "gid": "34376951"
      },
      {
        "gid": "34616206"
      },
      {
        "gid": "34690208"
      },
      {
        "gid": "34783734"
      },
      {
        "gid": "34860588"
      },
      {
        "gid": "34898046"
      },
      {
        "gid": "34948692"
      },
      {
        "gid": "35061675"
      },
      {
        "gid": "35066530"
      },
      {
        "gid": "35068692"
      },
      {
        "gid": "35071917"
      },
      {
        "gid": "35117621"
      },
      {
        "gid": "35167648"
      },
      {
        "gid": "35190912"
      },
      {
        "gid": "35210272"
      },
      {
        "gid": "35210771"
      },
      {
        "gid": "35212579"
      },
      {
        "gid": "35220668"
      },
      {
        "gid": "35266496"
      },
      {
        "gid": "35349173"
      },
      {
        "gid": "35387861"
      },
      {
        "gid": "36090644"
      },
      {
        "gid": "36260268"
      },
      {
        "gid": "36325233"
      },
      {
        "gid": "36811295"
      },
      {
        "gid": "37306171"
      },
      {
        "gid": "39222591"
      },
      {
        "gid": "39627096"
      },
      {
        "gid": "39749226"
      },
      {
        "gid": "41673938"
      },
      {
        "gid": "42824826"
      },
      {
        "gid": "43187270"
      }
    ]
  }
}