{
  "response": {
    "players": [
      {
        "steamid": "76561198326212913",
        "communityvisibilitystate": 3,
        "profilestate": 1,
        "personaname": "Dũng Nhỏ",
        "commentpermission": 1,
        "profileurl": "https://steamcommunity.com/id/mit1210/",
        "avatar": "https://avatars.steamstatic.com/d7016256c643aa27c1680e558868979ed97963ab.jpg",
        "avatarmedium": "https://avatars.steamstatic.com/d7016256c643aa27c1680e558868979ed97963ab_medium.jpg",
        "avatarfull": "https://avatars.steamstatic.com/d7016256c643aa27c1680e558868979ed97963ab_full.jpg",
        "avatarhash": "d7016256c643aa27c1680e558868979ed97963ab",
        "personastate": 0,
        "primaryclanid": "103582791455109943",
        "timecreated": 1471841908,
        "personastateflags": 0
      }
    ]
  }
}