{
  "response": {
    "players": [
      {
        "steamid": "76561198065058501",
        "communityvisibilitystate": 3,
        "profilestate": 1,
        "personaname": "B1",
        "commentpermission": 1,
        "profileurl": "https://steamcommunity.com/id/HDlThinh/",
        "avatar": "https://avatars.steamstatic.com/e4988b431e82998c30285307f29b766fdb215120.jpg",
        "avatarmedium": "https://avatars.steamstatic.com/e4988b431e82998c30285307f29b766fdb215120_medium.jpg",
        "avatarfull": "https://avatars.steamstatic.com/e4988b431e82998c30285307f29b766fdb215120_full.jpg",
        "avatarhash": "e4988b431e82998c30285307f29b766fdb215120",
        "personastate": 0,
        "primaryclanid": "103582791456192214",
        "timecreated": 1339292322,
        "personastateflags": 0,
        "loccountrycode": "VN"
      }
    ]
  }
}