{
  "response": {
    "players": [
      {
        "steamid": "76561198362468836",
        "communityvisibilitystate": 3,
        "profilestate": 1,
        "personaname": "как долго навсегд",
        "profileurl": "https://steamcommunity.com/id/hiimfreezing/",
        "avatar": "https://avatars.steamstatic.com/5e4de8a73b71e1c766f98fd1987aa0c91176a192.jpg",
        "avatarmedium": "https://avatars.steamstatic.com/5e4de8a73b71e1c766f98fd1987aa0c91176a192_medium.jpg",
        "avatarfull": "https://avatars.steamstatic.com/5e4de8a73b71e1c766f98fd1987aa0c91176a192_full.jpg",
        "avatarhash": "5e4de8a73b71e1c766f98fd1987aa0c91176a192",
        "personastate": 0,
        "primaryclanid": "103582791429521408",
        "timecreated": 1485506933,
        "personastateflags": 0,
        "loccountrycode": "VN",
        "locstatecode": "52"
      }
    ]
  }
}