{
  "response": {
    "game_count": 91,
    "games": [
      {
        "appid": 10,
        "name": "Counter-Strike",
        "playtime_forever": 0,
        "img_icon_url": "6b0312cda02f5f777efa2f3318c307ff9acafbb5",
        "content_descriptorids": [
          2,
          5
        ]
      },
      {
        "appid": 80,
        "name": "Counter-Strike: Condition Zero",
        "playtime_forever": 0,
        "img_icon_url": "077b050ef3e89cd84e2c5a575d78d53b54058236",
        "content_descriptorids": [
          2,
          5
        ]
      },
      {
        "appid": 100,
        "name": "Counter-Strike: Condition Zero Deleted Scenes",
        "playtime_forever": 0,
        "img_icon_url": "077b050ef3e89cd84e2c5a575d78d53b54058236"
      },
      {
        "appid": 550,
        "name": "Left 4 Dead 2",
        "playtime_forever": 1008,
        "img_icon_url": "7d5a243f9500d2f8467312822f8af2a2928777ed",
        "has_community_visible_stats": true,
        "content_descriptorids": [
          2,
          5
        ]
      },
      {
        "appid": 730,
        "name": "Counter-Strike 2",
        "playtime_2weeks": 1415,
        "playtime_forever": 135243,
        "img_icon_url": "8dbc71957312bbd3baea65848b545be9eae2a355",
        "has_community_visible_stats": true,
        "content_descriptorids": [
          2,
          5
        ]
      },
      {
        "appid": 1250,
        "name": "Killing Floor",
        "playtime_forever": 308,
        "img_icon_url": "d8a2d777cb4c59cf06aa244166db232336520547",
        "has_community_visible_stats": true,
        "content_descriptorids": [
          2,
          5
        ]
      },
      {
        "appid": 4000,
        "name": "Garry's Mod",
        "playtime_forever": 976,
        "img_icon_url": "4a6f25cfa2426445d0d9d6e233408de4d371ce8b",
        "has_community_visible_stats": true
      },
      {
        "appid": 9480,
        "name": "Saints Row 2",
        "playtime_forever": 15,
        "img_icon_url": "1a0aef912300d396a67f9eda9d8b4e66c41c9891",
        "content_descriptorids": [
          1,
          2,
          5
        ]
      },
      {
        "appid": 35420,
        "name": "Killing Floor Mod: Defence Alliance 2",
        "playtime_forever": 0,
        "img_icon_url": "ae7580a60cf77b754c723c72d5e31d530fbe7804",
        "has_community_visible_stats": true
      },
      {
        "appid": 35450,
        "name": "Rising Storm/Red Orchestra 2 Multiplayer",
        "playtime_forever": 13,
        "img_icon_url": "d70423dddb3bb2a144e38ab9cc811e6fda1eb622",
        "has_community_visible_stats": true,
        "content_descriptorids": [
          2,
          5
        ]
      },
      {
        "appid": 105600,
        "name": "Terraria",
        "playtime_forever": 2050,
        "img_icon_url": "858961e95fbf869f136e1770d586e0caefd4cfac",
        "has_community_visible_stats": true
      },
      {
        "appid": 108600,
        "name": "Project Zomboid",
        "playtime_2weeks": 757,
        "playtime_forever": 757,
        "img_icon_url": "2bd4642ae337e378e7b04a19d19683425c5f81a4",
        "content_descriptorids": [
          2,
          5
        ]
      },
      {
        "appid": 203160,
        "name": "Tomb Raider",
        "playtime_forever": 54,
        "img_icon_url": "3ee640a8aba6992678e36f4e40cba9c71c02348b",
        "has_community_visible_stats": true
      },
      {
        "appid": 207610,
        "name": "The Walking Dead",
        "playtime_forever": 0,
        "img_icon_url": "87a13ae0a2a76488792924aa8bb0dd8a7760f931",
        "has_community_visible_stats": true,
        "content_descriptorids": [
          2,
          5
        ]
      },
      {
        "appid": 218620,
        "name": "PAYDAY 2",
        "playtime_forever": 62,
        "img_icon_url": "a6abc0d0c1e79c0b5b0f5c8ab81ce9076a542414",
        "has_community_visible_stats": true,
        "content_descriptorids": [
          2,
          5
        ]
      },
      {
        "appid": 222880,
        "name": "Insurgency",
        "playtime_forever": 0,
        "img_icon_url": "b072fc4239951c1952f4877edde340419438b528",
        "has_community_visible_stats": true,
        "content_descriptorids": [
          2,
          5
        ]
      },
      {
        "appid": 227300,
        "name": "Euro Truck Simulator 2",
        "playtime_forever": 472,
        "img_icon_url": "adc18a4fc9adc0330144b76d61cbda68bb2394a0",
        "has_community_visible_stats": true
      },
      {
        "appid": 230410,
        "name": "Warframe",
        "playtime_forever": 413,
        "img_icon_url": "22064646470f4c53388ba87774c7ac10f0a91ffa",
        "has_community_visible_stats": true,
        "content_descriptorids": [
          2,
          5
        ]
      },
      {
        "appid": 233130,
        "name": "Shadow Warrior",
        "playtime_forever": 0,
        "img_icon_url": "5d7c205ce18f17a99c95ff81499c2f496e0570f2",
        "has_community_visible_stats": true,
        "content_descriptorids": [
          2,
          5
        ]
      },
      {
        "appid": 238320,
        "name": "Outlast",
        "playtime_forever": 0,
        "img_icon_url": "46bd3df92d4693d3b2af113bf8f31c2cbdadb20a",
        "has_community_visible_stats": true,
        "content_descriptorids": [
          1,
          2,
          5
        ]
      },
      {
        "appid": 242760,
        "name": "The Forest",
        "playtime_forever": 1089,
        "img_icon_url": "3a6847f6ac5879e48531db52261771d5e22904ac",
        "has_community_visible_stats": true,
        "content_descriptorids": [
          2,
          5
        ]
      },
      {
        "appid": 252490,
        "name": "Rust",
        "playtime_forever": 18085,
        "img_icon_url": "820be4782639f9c4b64fa3ca7e6c26a95ae4fd1c",
        "has_community_visible_stats": true,
        "content_descriptorids": [
          1,
          2,
          5
        ]
      },
      {
        "appid": 252950,
        "name": "Rocket League",
        "playtime_forever": 1496,
        "img_icon_url": "9ad6dd3d173523354385955b5fb2af87639c4163",
        "has_community_visible_stats": true
      },
      {
        "appid": 255520,
        "name": "Viscera Cleanup Detail: Shadow Warrior",
        "playtime_forever": 0,
        "img_icon_url": "56c3840d52a0da4f397d9991d368c75ed53d99fa",
        "has_community_visible_stats": true,
        "content_descriptorids": [
          2,
          5
        ]
      },
      {
        "appid": 255710,
        "name": "Cities: Skylines",
        "playtime_forever": 67,
        "img_icon_url": "6cf7b10dd29db28448ef79698ed2118a03617d63",
        "has_community_visible_stats": true
      },
      {
        "appid": 265550,
        "name": "Dead Rising 3",
        "playtime_forever": 740,
        "img_icon_url": "f5cdf9af7b3ab97308c13a326fe22bad9445419c",
        "has_community_visible_stats": true
      },
      {
        "appid": 265630,
        "name": "Fistful of Frags",
        "playtime_forever": 49,
        "img_icon_url": "e70c19e10125ea3f221666327af2b90f3fcecad9",
        "has_community_visible_stats": true,
        "has_leaderboards": true,
        "content_descriptorids": [
          2,
          5
        ]
      },
      {
        "appid": 271590,
        "name": "Grand Theft Auto V Legacy",
        "playtime_forever": 8680,
        "img_icon_url": "1e72f87eb927fa1485e68aefaff23c7fd7178251",
        "has_community_visible_stats": true,
        "content_descriptorids": [
          5
        ]
      },
      {
        "appid": 280790,
        "name": "Creativerse",
        "playtime_forever": 137,
        "img_icon_url": "e4937c3f653f127bdfddc17a8a544f887775e6be"
      },
      {
        "appid": 289070,
        "name": "Sid Meier's Civilization VI",
        "playtime_forever": 35,
        "img_icon_url": "9dc914132fec244adcede62fb8e7524a72a7398c",
        "has_community_visible_stats": true
      },
      {
        "appid": 291550,
        "name": "Brawlhalla",
        "playtime_forever": 1048,
        "img_icon_url": "c43fac31b8bf8821764603a14d09412bc3d45f66",
        "has_community_visible_stats": true
      },
      {
        "appid": 304050,
        "name": "Trove",
        "playtime_forever": 4,
        "img_icon_url": "76b62601bb6f0551c415697fe92a6653340f4a5e",
        "has_community_visible_stats": true
      },
      {
        "appid": 304930,
        "name": "Unturned",
        "playtime_forever": 397,
        "img_icon_url": "e18009fb628b35953826efe47dc3be556b689f4c",
        "has_community_visible_stats": true
      },
      {
        "appid": 321040,
        "name": "DiRT 3 Complete Edition",
        "playtime_forever": 17,
        "img_icon_url": "fdfb3aa153b57d6ae6cd8099cb4456b3d5b182b6",
        "has_community_visible_stats": true
      },
      {
        "appid": 322330,
        "name": "Don't Starve Together",
        "playtime_forever": 1034,
        "img_icon_url": "a80aa6cff8eebc1cbc18c367d9ab063e1553b0ee"
      },
      {
        "appid": 323580,
        "name": "Jotun: Valhalla Edition",
        "playtime_forever": 4,
        "img_icon_url": "69b336a11a1e8acee4034b970a89c1df7cf53b32",
        "has_community_visible_stats": true
      },
      {
        "appid": 327690,
        "name": "Gigantic",
        "playtime_forever": 12,
        "img_icon_url": "992a647ce69a8a3548f55cd4a746408abfdac7f6"
      },
      {
        "appid": 333930,
        "name": "Dirty Bomb",
        "playtime_forever": 37,
        "img_icon_url": "48a3c464019fc161c2ea17334ca8d545a846a98e",
        "has_community_visible_stats": true
      },
      {
        "appid": 339610,
        "name": "FreeStyle 2: Street Basketball",
        "playtime_forever": 3480,
        "img_icon_url": "368f89b5ecc999f1956a98a9bdb86f4d6acb243d"
      },
      {
        "appid": 346110,
        "name": "ARK: Survival Evolved",
        "playtime_forever": 252,
        "img_icon_url": "fef1799533131c10f538d2dd697bbbd89e663265",
        "has_community_visible_stats": true
      },
      {
        "appid": 359550,
        "name": "Tom Clancy's Rainbow Six® Siege X",
        "playtime_forever": 4247,
        "img_icon_url": "624745d333ac54aedb1ee911013e2edb7722550e",
        "content_descriptorids": [
          5
        ]
      },
      {
        "appid": 389400,
        "name": "The chronicles of Emerland. Solitaire.",
        "playtime_forever": 0,
        "img_icon_url": "c037d5cb88007fee02d245d1a6c36d9570e03719",
        "has_community_visible_stats": true
      },
      {
        "appid": 389700,
        "name": "My Bones",
        "playtime_forever": 0,
        "img_icon_url": "4313263835fdc437f71894eee33521ecff7bea6f"
      },
      {
        "appid": 391460,
        "name": "WARMODE",
        "playtime_forever": 29,
        "img_icon_url": "e42a4a7627c4806f29d40e4564d3b20092e16b2a"
      },
      {
        "appid": 393420,
        "name": "Hurtworld",
        "playtime_forever": 26,
        "img_icon_url": "6d5ae57f85d8d2af758afa89df4369da699900dc",
        "content_descriptorids": [
          5
        ]
      },
      {
        "appid": 397900,
        "name": "Business Tour - Online Multiplayer Board Game",
        "playtime_forever": 223,
        "img_icon_url": "b6ce52a576e99f54c5d18f675540b9c3ee70ed47",
        "has_community_visible_stats": true
      },
      {
        "appid": 407530,
        "name": "ARK: Survival Of The Fittest",
        "playtime_forever": 352,
        "img_icon_url": "807c673cddebbfee0700a947a75f4872ad136e9b"
      },
      {
        "appid": 413150,
        "name": "Stardew Valley",
        "playtime_forever": 744,
        "img_icon_url": "35d1377200084a4034238c05b0c8930451e2fb40",
        "has_community_visible_stats": true
      },
      {
        "appid": 428630,
        "name": "White Mirror",
        "playtime_forever": 0,
        "img_icon_url": "d4421f296f27229e1947112832409ac0fa05f051"
      },
      {
        "appid": 431960,
        "name": "Wallpaper Engine",
        "playtime_forever": 550,
        "img_icon_url": "72edaed9d748c6cf7397ffb1c83f0b837b9ebd9d",
        "has_community_visible_stats": true
      },
      {
        "appid": 433850,
        "name": "Z1 Battle Royale",
        "playtime_forever": 11,
        "img_icon_url": "aee7491abfd812e2fbb4ec3326ad5f4b85c8137a",
        "content_descriptorids": [
          2,
          5
        ]
      },
      {
        "appid": 438100,
        "name": "VRChat",
        "playtime_forever": 443,
        "img_icon_url": "52c5f93bd9f8de008307f5fad95023600267462c"
      },
      {
        "appid": 440900,
        "name": "Conan Exiles",
        "playtime_forever": 178,
        "img_icon_url": "399859f8bdaeef066f14029d5f1910960545fbd9",
        "has_community_visible_stats": true,
        "content_descriptorids": [
          1,
          2,
          5
        ]
      },
      {
        "appid": 444090,
        "name": "Paladins",
        "playtime_forever": 67,
        "img_icon_url": "1565119c17f532338a0645b98e69e1fc1df0c29e",
        "has_community_visible_stats": true
      },
      {
        "appid": 451350,
        "name": "Tropical Fish Shop 2",
        "playtime_forever": 1,
        "img_icon_url": "a4e9f3b55d0dbf71adb5c21d327231e4fceaaa1e"
      },
      {
        "appid": 477160,
        "name": "Human Fall Flat",
        "playtime_forever": 853,
        "img_icon_url": "15c6f6a4d69633a63ee410b24a2417f16d803b06",
        "has_community_visible_stats": true
      },
      {
        "appid": 506540,
        "name": "Last Man Standing",
        "playtime_forever": 886,
        "img_icon_url": "dbc9c2863f6b352c91fa6b347397320ea5ef19be"
      },
      {
        "appid": 550650,
        "name": "Black Squad",
        "playtime_forever": 25,
        "img_icon_url": "213a736d8c5b75998b671de25e6621d1e7bc122a",
        "has_community_visible_stats": true,
        "content_descriptorids": [
          1,
          5
        ]
      },
      {
        "appid": 578080,
        "name": "PUBG: BATTLEGROUNDS",
        "playtime_forever": 5366,
        "img_icon_url": "609f27278aa70697c13bf99f32c5a0248c381f9d",
        "has_community_visible_stats": true,
        "content_descriptorids": [
          2,
          5
        ]
      },
      {
        "appid": 584890,
        "name": "Stayin' Alive",
        "playtime_forever": 8,
        "img_icon_url": "b2584e4b8b7689a06c2201991e04de8f3e8b40f5",
        "has_community_visible_stats": true,
        "content_descriptorids": [
          2,
          5
        ]
      },
      {
        "appid": 623990,
        "name": "Tom Clancy's Rainbow Six Siege - Test Server",
        "playtime_forever": 0,
        "img_icon_url": "20deaf466474f76f2ffdb345fe56f40fe3af74c0"
      },
      {
        "appid": 648800,
        "name": "Raft",
        "playtime_forever": 1821,
        "img_icon_url": "6a9ae357c4133b1b631b520edd25b1974f3afb68",
        "has_community_visible_stats": true
      },
      {
        "appid": 657200,
        "name": "Hand Simulator",
        "playtime_forever": 57,
        "img_icon_url": "b2ecce2712d54f1978496919c734b6da1d1cbb5e",
        "has_community_visible_stats": true
      },
      {
        "appid": 670290,
        "name": "Real Pool 3D - Poolians",
        "playtime_forever": 451,
        "img_icon_url": "b74acc3e1996c8cb9ce9e2933c190575fa0be457"
      },
      {
        "appid": 671860,
        "name": "BattleBit Remastered",
        "playtime_forever": 556,
        "img_icon_url": "84d4db032ad4d637b97e9a25f7d3da70b6fd6257",
        "content_descriptorids": [
          5
        ]
      },
      {
        "appid": 705210,
        "name": "Cube Racer",
        "playtime_forever": 483,
        "img_icon_url": "729bcef1b009c32e0c99b7418bac2e5873ae872f",
        "has_community_visible_stats": true
      },
      {
        "appid": 728880,
        "name": "Overcooked! 2",
        "playtime_forever": 156,
        "img_icon_url": "bac36f471109038ae0b40619de4109d475f86a54",
        "has_community_visible_stats": true
      },
      {
        "appid": 823130,
        "name": "Totally Accurate Battlegrounds",
        "playtime_forever": 12,
        "img_icon_url": "920902c516d435c3d9a6c5ef92e3cd4372f9314b"
      },
      {
        "appid": 835570,
        "name": "Conqueror's Blade",
        "playtime_forever": 1792,
        "img_icon_url": "146c4d41ab8c557a2a9ff1818d438e74de55942a",
        "has_community_visible_stats": true,
        "content_descriptorids": [
          2,
          5
        ]
      },
      {
        "appid": 863550,
        "name": "HITMAN™ 2",
        "playtime_forever": 0,
        "img_icon_url": "3f7c071da7a338e03f6243b73c02c072f1bacee9",
        "has_community_visible_stats": true,
        "content_descriptorids": [
          2,
          5
        ]
      },
      {
        "appid": 880940,
        "name": "Pummel Party",
        "playtime_forever": 398,
        "img_icon_url": "0e2e222010d009ca46b575cc5c53a23250434341",
        "has_community_visible_stats": true
      },
      {
        "appid": 884660,
        "name": "CRSED: Cuisine Royale",
        "playtime_forever": 46,
        "img_icon_url": "e4c07740f6f49341f830565c91e05bca0bb10d64",
        "has_community_visible_stats": true,
        "content_descriptorids": [
          2,
          5
        ]
      },
      {
        "appid": 931180,
        "name": "Conan Exiles - Public Beta Client",
        "playtime_forever": 0,
        "img_icon_url": "67a32c9bdd0738df619162c70bdebfe8a735abec"
      },
      {
        "appid": 1088150,
        "name": "Scribble It!",
        "playtime_forever": 59,
        "img_icon_url": "a7a683dce57646a59a0fca326d0ceae5a74b8c2f",
        "has_community_visible_stats": true
      },
      {
        "appid": 1097150,
        "name": "Fall Guys",
        "playtime_forever": 155,
        "img_icon_url": "6c027709b9eb1417c993bc7d513b97b232002368",
        "has_community_visible_stats": true
      },
      {
        "appid": 1131720,
        "name": "Prop and Seek",
        "playtime_forever": 416,
        "img_icon_url": "c580682bdb70b0a9d5f4d5374f2e2fad8ca75438",
        "has_community_visible_stats": true,
        "has_leaderboards": true
      },
      {
        "appid": 1172620,
        "name": "Sea of Thieves",
        "playtime_forever": 332,
        "img_icon_url": "f95f362708fc326511c5d86566c447ee625bf776",
        "has_community_visible_stats": true
      },
      {
        "appid": 1203220,
        "name": "NARAKA: BLADEPOINT",
        "playtime_forever": 10177,
        "img_icon_url": "8055e7baa81ce2084d7daa42233983967956abb0",
        "has_community_visible_stats": true
      },
      {
        "appid": 1260320,
        "name": "Party Animals",
        "playtime_forever": 425,
        "img_icon_url": "868cd2d22c96076658ff5b572c4dc790c200de7e",
        "has_community_visible_stats": true
      },
      {
        "appid": 1273710,
        "name": "King of Crabs",
        "playtime_forever": 52,
        "img_icon_url": "ee2469b799c84eca9681baf6fdabd1fef8979164",
        "has_community_visible_stats": true
      },
      {
        "appid": 1305420,
        "name": "Agrou",
        "playtime_forever": 0,
        "img_icon_url": "f1cf3a79549ee9b856ae2a0066ad3813ff8ee142",
        "has_community_visible_stats": true
      },
      {
        "appid": 1326470,
        "name": "Sons Of The Forest",
        "playtime_forever": 2202,
        "img_icon_url": "bd28fe592b339cff5a3eef743f31e3166c984c68",
        "has_community_visible_stats": true,
        "content_descriptorids": [
          1,
          2,
          5
        ]
      },
      {
        "appid": 1474700,
        "name": "MONOPOLY Poker",
        "playtime_forever": 15,
        "img_icon_url": "1330949c2110d65a9393d68782d8871fca2329ac",
        "has_community_visible_stats": true
      },
      {
        "appid": 1506830,
        "name": "FIFA 22",
        "playtime_forever": 153,
        "img_icon_url": "97e6ad42ea46c285ba047e8e7fd0487688e9d4c1",
        "has_community_visible_stats": true
      },
      {
        "appid": 1568590,
        "name": "Goose Goose Duck",
        "playtime_forever": 725,
        "img_icon_url": "3b802d5010d6d5d72c93a8565b260c6042cc9390",
        "has_community_visible_stats": true
      },
      {
        "appid": 1794680,
        "name": "Vampire Survivors",
        "playtime_forever": 578,
        "img_icon_url": "3677cf1be3be1f4ea42261c62ce10519715ade58",
        "has_community_visible_stats": true
      },
      {
        "appid": 1966720,
        "name": "Lethal Company",
        "playtime_forever": 240,
        "img_icon_url": "8393f321a62a9ef0be762c81565d2caea4fb7da6",
        "content_descriptorids": [
          2,
          5
        ]
      },
      {
        "appid": 2357570,
        "name": "Overwatch® 2",
        "playtime_forever": 445,
        "img_icon_url": "da42bd294c941d5947b1bc2c2b2efa1313d36a91",
        "has_community_visible_stats": true
      },
      {
        "appid": 2709570,
        "name": "Supermarket Together",
        "playtime_forever": 232,
        "img_icon_url": "df024275a7ba53c79008b45c0d74b4a2e6a2069b",
        "has_community_visible_stats": true
      },
      {
        "appid": 2767030,
        "name": "Marvel Rivals",
        "playtime_forever": 820,
        "img_icon_url": "839b4712925b95702ca56e0c4d399adf54f4d617",
        "has_community_visible_stats": true
      },
      {
        "appid": 3240220,
        "name": "Grand Theft Auto V Enhanced",
        "playtime_forever": 0,
        "img_icon_url": "8355a7bbdb704f727bfba80ec56bc7228991338e",
        "has_community_visible_stats": true,
        "content_descriptorids": [
          1,
          2,
          5
        ]
      }
    ]
  }
}